{
  "header": {
    "message_id": 497,
    "timestamp": "2025-12-12T06:26:28.640972Z",
    "source": "EPS_MCU",
    "message_type": "SUMMARY",
    "priority": "MEDIUM",
    "version": "1.0"
  },
  "payload": {
    "rule_triggered": "R5",
    "values": {},
    "actions_taken": [
      "INCREASE_LOGGING",
      "LED_YELLOW"
    ],
    "emergency_level": "MEDIUM",
    "temporal_window": {
      "window_size_seconds": 30.0,
      "data_points_count": 100,
      "sensor_data": [
        {
          "timestamp": "2025-12-12 14:22:09.010811",
          "V_batt": 8.061,
          "I_batt": 1.841,
          "T_batt": 3.1,
          "V_solar": 16.427,
          "I_solar": 1.315,
          "V_bus": 7.978,
          "I_bus": 0.666,
          "T_eps": 6.6,
          "SOC": 64.7,
          "anomaly_type": "normal",
          "orbit_sunlight": true,
          "P_batt": 14.840301,
          "P_solar": 21.601505,
          "P_bus": 5.313348,
          "converter_ratio": 0.4856638461070189,
          "charge_efficiency": 0.6870031046447921,
          "delta_V_batt": -0.1229999999999993,
          "delta_I_batt": -0.3270000000000002,
          "delta_T_batt": -0.2999999999999998,
          "delta_V_bus": -0.0990000000000002,
          "delta_I_bus": 0.003,
          "delta_SOC": -7.599999999999994,
          "rolling_std_V_batt": 0.4648691572188127,
          "rolling_mean_V_batt": 8.017,
          "rolling_std_I_batt": 1.2617657116561332,
          "rolling_mean_I_batt": 1.0376,
          "rolling_std_T_batt": 4.969339325637989,
          "rolling_mean_T_batt": 7.109999999999999,
          "V_batt_V_bus_ratio": 1.0104036099273002,
          "power_balance": 1.447855999999999
        },
        {
          "timestamp": "2025-12-12 14:22:26.290811",
          "V_batt": 8.246,
          "I_batt": 2.406,
          "T_batt": 4.3,
          "V_solar": 17.633,
          "I_solar": 1.521,
          "V_bus": 8.111,
          "I_bus": 0.672,
          "T_eps": 6.9,
          "SOC": 75.6,
          "anomaly_type": "normal",
          "orbit_sunlight": true,
          "P_batt": 19.839876000000004,
          "P_solar": 26.819793,
          "P_bus": 5.450592000000001,
          "converter_ratio": 0.4599897918675212,
          "charge_efficiency": 0.7397475439128112,
          "delta_V_batt": 0.1850000000000005,
          "delta_I_batt": 0.5650000000000002,
          "delta_T_batt": 1.1999999999999995,
          "delta_V_bus": 0.1330000000000009,
          "delta_I_bus": 0.006,
          "delta_SOC": 10.899999999999991,
          "rolling_std_V_batt": 0.4573638959661432,
          "rolling_mean_V_batt": 8.006200000000002,
          "rolling_std_I_batt": 1.334495447725468,
          "rolling_mean_I_batt": 1.1569,
          "rolling_std_T_batt": 5.035474158408408,
          "rolling_mean_T_batt": 6.959999999999999,
          "V_batt_V_bus_ratio": 1.0166440636173095,
          "power_balance": 1.529324999999992
        },
        {
          "timestamp": "2025-12-12 14:22:43.570811",
          "V_batt": 8.253,
          "I_batt": 2.087,
          "T_batt": 4.4,
          "V_solar": 17.928,
          "I_solar": 1.315,
          "V_bus": 8.161,
          "I_bus": 0.678,
          "T_eps": 7.0,
          "SOC": 76.9,
          "anomaly_type": "normal",
          "orbit_sunlight": true,
          "P_batt": 17.224011,
          "P_solar": 23.57532,
          "P_bus": 5.533158,
          "converter_ratio": 0.4552097278000892,
          "charge_efficiency": 0.7305950035884985,
          "delta_V_batt": 0.0069999999999996,
          "delta_I_batt": -0.3189999999999999,
          "delta_T_batt": 0.1000000000000005,
          "delta_V_bus": 0.0499999999999989,
          "delta_I_bus": 0.006,
          "delta_SOC": 1.3000000000000114,
          "rolling_std_V_batt": 0.4629883727841655,
          "rolling_mean_V_batt": 8.0197,
          "rolling_std_I_batt": 1.3665385956252136,
          "rolling_mean_I_batt": 1.2332,
          "rolling_std_T_batt": 5.088123426175789,
          "rolling_mean_T_batt": 6.83,
          "V_batt_V_bus_ratio": 1.0112731282931011,
          "power_balance": 0.8181510000000003
        },
        {
          "timestamp": "2025-12-12 14:23:00.850811",
          "V_batt": 8.102,
          "I_batt": 1.275,
          "T_batt": 3.4,
          "V_solar": 16.168,
          "I_solar": 1.013,
          "V_bus": 8.02,
          "I_bus": 0.675,
          "T_eps": 7.6,
          "SOC": 65.9,
          "anomaly_type": "normal",
          "orbit_sunlight": true,
          "P_batt": 10.33005,
          "P_solar": 16.378183999999997,
          "P_bus": 5.4135,
          "converter_ratio": 0.4960415635823849,
          "charge_efficiency": 0.6307201091403053,
          "delta_V_batt": -0.1509999999999998,
          "delta_I_batt": -0.8120000000000003,
          "delta_T_batt": -1.0000000000000004,
          "delta_V_bus": -0.141,
          "delta_I_bus": -0.003,
          "delta_SOC": -11.0,
          "rolling_std_V_batt": 0.4632002806562151,
          "rolling_mean_V_batt": 8.0335,
          "rolling_std_I_batt": 0.7614511292408861,
          "rolling_mean_I_batt": 1.5616,
          "rolling_std_T_batt": 4.06788233195914,
          "rolling_mean_T_batt": 5.59,
          "V_batt_V_bus_ratio": 1.0102244389027433,
          "power_balance": 0.6346339999999975
        },
        {
          "timestamp": "2025-12-12 14:23:18.130811",
          "V_batt": 8.558,
          "I_batt": 1.49,
          "T_batt": -2.8,
          "V_solar": 16.992,
          "I_solar": 0.943,
          "V_bus": 7.816,
          "I_bus": 0.676,
          "T_eps": -7.1,
          "SOC": 54.0,
          "anomaly_type": "batt_overvoltage",
          "orbit_sunlight": true,
          "P_batt": 12.75142,
          "P_solar": 16.023456,
          "P_bus": 5.283616,
          "converter_ratio": 0.4599811676082862,
          "charge_efficiency": 0.7957971114346368,
          "delta_V_batt": 0.4559999999999995,
          "delta_I_batt": 0.215,
          "delta_T_batt": -6.199999999999999,
          "delta_V_bus": -0.2039999999999997,
          "delta_I_bus": 0.001,
          "delta_SOC": -11.900000000000006,
          "rolling_std_V_batt": 0.4880241455775153,
          "rolling_mean_V_batt": 8.0627,
          "rolling_std_I_batt": 0.6843736471320966,
          "rolling_mean_I_batt": 1.6507999999999998,
          "rolling_std_T_batt": 4.863572075474145,
          "rolling_mean_T_batt": 4.81,
          "V_batt_V_bus_ratio": 1.094933469805527,
          "power_balance": -2.0115800000000004
        },
        {
          "timestamp": "2025-12-12 14:23:18.130811",
          "V_batt": 8.009,
          "I_batt": 0.743,
          "T_batt": 1.6,
          "V_solar": 15.945,
          "I_solar": 0.758,
          "V_bus": 7.956,
          "I_bus": 0.676,
          "T_eps": 6.4,
          "SOC": 63.0,
          "anomaly_type": "normal",
          "orbit_sunlight": true,
          "P_batt": 5.950687,
          "P_solar": 12.08631,
          "P_bus": 5.378256,
          "converter_ratio": 0.4989651928504233,
          "charge_efficiency": 0.4923493605575233,
          "delta_V_batt": -0.5489999999999995,
          "delta_I_batt": -0.747,
          "delta_T_batt": 4.4,
          "delta_V_bus": 0.1400000000000005,
          "delta_I_bus": 0.0,
          "delta_SOC": 9.0,
          "rolling_std_V_batt": 0.4881139325107492,
          "rolling_mean_V_batt": 8.0619,
          "rolling_std_I_batt": 0.6681435723954333,
          "rolling_mean_I_batt": 1.4755,
          "rolling_std_T_batt": 4.949175015427502,
          "rolling_mean_T_batt": 4.39,
          "V_batt_V_bus_ratio": 1.0066616390145802,
          "power_balance": 0.7573670000000003
        },
        {
          "timestamp": "2025-12-12 14:23:35.410811",
          "V_batt": 8.153,
          "I_batt": 1.118,
          "T_batt": 1.1,
          "V_solar": 16.973,
          "I_solar": 0.919,
          "V_bus": 8.107,
          "I_bus": 0.683,
          "T_eps": 4.8,
          "SOC": 71.6,
          "anomaly_type": "normal",
          "orbit_sunlight": true,
          "P_batt": 9.115054,
          "P_solar": 15.598187,
          "P_bus": 5.537081,
          "converter_ratio": 0.4776409591704472,
          "charge_efficiency": 0.5843662471798806,
          "delta_V_batt": 0.1440000000000001,
          "delta_I_batt": 0.3750000000000001,
          "delta_T_batt": -0.5,
          "delta_V_bus": 0.1509999999999989,
          "delta_I_bus": 0.007,
          "delta_SOC": 8.599999999999994,
          "rolling_std_V_batt": 0.4762621243717661,
          "rolling_mean_V_batt": 8.038499999999999,
          "rolling_std_I_batt": 0.5837315307570753,
          "rolling_mean_I_batt": 1.5415,
          "rolling_std_T_batt": 5.040734073525246,
          "rolling_mean_T_batt": 3.97,
          "V_batt_V_bus_ratio": 1.0056741087948688,
          "power_balance": 0.946051999999999
        },
        {
          "timestamp": "2025-12-12 14:23:52.690811",
          "V_batt": 8.131,
          "I_batt": 1.942,
          "T_batt": 2.2,
          "V_solar": 15.363,
          "I_solar": 1.467,
          "V_bus": 8.016,
          "I_bus": 0.675,
          "T_eps": 4.0,
          "SOC": 68.8,
          "anomaly_type": "normal",
          "orbit_sunlight": true,
          "P_batt": 15.790402,
          "P_solar": 22.537521,
          "P_bus": 5.4108,
          "converter_ratio": 0.5217730911931263,
          "charge_efficiency": 0.700627278394993,
          "delta_V_batt": -0.0220000000000002,
          "delta_I_batt": 0.8239999999999998,
          "delta_T_batt": 1.1,
          "delta_V_bus": -0.0909999999999993,
          "delta_I_bus": -0.008,
          "delta_SOC": -2.799999999999997,
          "rolling_std_V_batt": 0.1559761021581329,
          "rolling_mean_V_batt": 8.175899999999999,
          "rolling_std_I_batt": 0.5973742917505263,
          "rolling_mean_I_batt": 1.5806,
          "rolling_std_T_batt": 2.1863211109071345,
          "rolling_mean_T_batt": 2.5,
          "V_batt_V_bus_ratio": 1.0143463073852297,
          "power_balance": 1.3363190000000014
        },
        {
          "timestamp": "2025-12-12 14:24:09.970811",
          "V_batt": 7.436,
          "I_batt": -0.699,
          "T_batt": -3.7,
          "V_solar": 0.842,
          "I_solar": 0.066,
          "V_bus": 7.394,
          "I_bus": 0.697,
          "T_eps": -0.9,
          "SOC": 28.4,
          "anomaly_type": "normal",
          "orbit_sunlight": false,
          "P_batt": -5.197763999999999,
          "P_solar": 0.055572,
          "P_bus": 5.153618,
          "converter_ratio": 8.78147268408551,
          "charge_efficiency": 0.0,
          "delta_V_batt": -0.6950000000000003,
          "delta_I_batt": -2.641,
          "delta_T_batt": -5.9,
          "delta_V_bus": -0.6219999999999999,
          "delta_I_bus": 0.0219999999999999,
          "delta_SOC": -40.4,
          "rolling_std_V_batt": 0.2817106671746713,
          "rolling_mean_V_batt": 8.113299999999999,
          "rolling_std_I_batt": 0.9122017868870892,
          "rolling_mean_I_batt": 1.4371,
          "rolling_std_T_batt": 2.824889378364768,
          "rolling_mean_T_batt": 1.7,
          "V_batt_V_bus_ratio": 1.0056802813091696,
          "power_balance": 0.0997179999999993
        },
        {
          "timestamp": "2025-12-12 14:24:27.250811",
          "V_batt": 7.572,
          "I_batt": -0.697,
          "T_batt": -9.5,
          "V_solar": 0.883,
          "I_solar": 0.105,
          "V_bus": 7.523,
          "I_bus": 0.677,
          "T_eps": -6.5,
          "SOC": 35.8,
          "anomaly_type": "normal",
          "orbit_sunlight": false,
          "P_batt": -5.277684,
          "P_solar": 0.0927149999999999,
          "P_bus": 5.093071,
          "converter_ratio": 8.519818799546998,
          "charge_efficiency": 0.0,
          "delta_V_batt": 0.1360000000000001,
          "delta_I_batt": 0.002,
          "delta_T_batt": -5.8,
          "delta_V_bus": 0.1289999999999995,
          "delta_I_bus": -0.0199999999999999,
          "delta_SOC": 7.399999999999999,
          "rolling_std_V_batt": 0.3274142635866634,
          "rolling_mean_V_batt": 8.0521,
          "rolling_std_I_batt": 1.0897682934153166,
          "rolling_mean_I_batt": 1.1506,
          "rolling_std_T_batt": 4.443834680393113,
          "rolling_mean_T_batt": 0.4100000000000001,
          "V_batt_V_bus_ratio": 1.006513359032301,
          "power_balance": 0.2773279999999998
        }
      ]
    }
  }
}