{
  "header": {
    "message_id": 170,
    "timestamp": "2025-12-12T06:26:27.270852Z",
    "source": "EPS_MCU",
    "message_type": "SUMMARY",
    "priority": "MEDIUM",
    "version": "1.0"
  },
  "payload": {
    "rule_triggered": "R4",
    "values": {},
    "ratio": 0.5186759992150193,
    "actions_taken": [
      "REDUCE_LOAD",
      "LED_YELLOW"
    ],
    "emergency_level": "MEDIUM",
    "temporal_window": {
      "window_size_seconds": 30.0,
      "data_points_count": 100,
      "sensor_data": [
        {
          "timestamp": "2025-12-12 12:38:28.210811",
          "V_batt": 8.026,
          "I_batt": 1.149,
          "T_batt": 15.5,
          "V_solar": 15.931,
          "I_solar": 0.801,
          "V_bus": 7.962,
          "I_bus": 0.326,
          "T_eps": 13.8,
          "SOC": 62.3,
          "anomaly_type": "normal",
          "orbit_sunlight": true,
          "P_batt": 9.221874,
          "P_solar": 12.760731,
          "P_bus": 2.595612,
          "converter_ratio": 0.4997803025547674,
          "charge_efficiency": 0.72267599716662,
          "delta_V_batt": 0.0129999999999999,
          "delta_I_batt": -1.348,
          "delta_T_batt": -0.3000000000000007,
          "delta_V_bus": 0.0510000000000001,
          "delta_I_bus": 0.018,
          "delta_SOC": -0.9000000000000057,
          "rolling_std_V_batt": 0.0892811414701927,
          "rolling_mean_V_batt": 8.132299999999999,
          "rolling_std_I_batt": 1.2394964075964252,
          "rolling_mean_I_batt": 1.2743,
          "rolling_std_T_batt": 17.498050685084266,
          "rolling_mean_T_batt": 18.98,
          "V_batt_V_bus_ratio": 1.008038181361467,
          "power_balance": 0.943245
        },
        {
          "timestamp": "2025-12-12 12:38:45.490811",
          "V_batt": 8.345,
          "I_batt": 1.865,
          "T_batt": 16.0,
          "V_solar": 16.327,
          "I_solar": 1.189,
          "V_bus": 8.252,
          "I_bus": 0.331,
          "T_eps": 14.6,
          "SOC": 81.7,
          "anomaly_type": "normal",
          "orbit_sunlight": true,
          "P_batt": 15.563425,
          "P_solar": 19.412803000000004,
          "P_bus": 2.731412,
          "converter_ratio": 0.5054204691615116,
          "charge_efficiency": 0.8017093152390202,
          "delta_V_batt": 0.3190000000000008,
          "delta_I_batt": 0.716,
          "delta_T_batt": 0.5,
          "delta_V_bus": 0.2900000000000009,
          "delta_I_bus": 0.005,
          "delta_SOC": 19.40000000000001,
          "rolling_std_V_batt": 0.108819728603466,
          "rolling_mean_V_batt": 8.1592,
          "rolling_std_I_batt": 1.1999620179174186,
          "rolling_mean_I_batt": 1.2242000000000002,
          "rolling_std_T_batt": 17.522369829576267,
          "rolling_mean_T_batt": 18.77,
          "V_batt_V_bus_ratio": 1.0112699951526902,
          "power_balance": 1.1179660000000031
        },
        {
          "timestamp": "2025-12-12 12:39:02.770811",
          "V_batt": 8.236,
          "I_batt": 1.898,
          "T_batt": 16.5,
          "V_solar": 14.198,
          "I_solar": 0.348,
          "V_bus": 8.133,
          "I_bus": 0.324,
          "T_eps": 14.1,
          "SOC": 73.5,
          "anomaly_type": "solar_partial_failure",
          "orbit_sunlight": true,
          "P_batt": 15.631928,
          "P_solar": 4.940904,
          "P_bus": 2.635092,
          "converter_ratio": 0.5728271587547541,
          "charge_efficiency": 3.163778936000376,
          "delta_V_batt": -0.1089999999999999,
          "delta_I_batt": 0.0329999999999999,
          "delta_T_batt": 0.5,
          "delta_V_bus": -0.1190000000000015,
          "delta_I_bus": -0.007,
          "delta_SOC": -8.200000000000003,
          "rolling_std_V_batt": 0.1115232412250114,
          "rolling_mean_V_batt": 8.1661,
          "rolling_std_I_batt": 1.2112533683017033,
          "rolling_mean_I_batt": 1.3245,
          "rolling_std_T_batt": 16.34719139995207,
          "rolling_mean_T_batt": 20.38,
          "V_batt_V_bus_ratio": 1.0126644534612077,
          "power_balance": -13.326116
        },
        {
          "timestamp": "2025-12-12 12:39:02.770811",
          "V_batt": 8.312,
          "I_batt": 2.489,
          "T_batt": 15.9,
          "V_solar": 15.865,
          "I_solar": 1.871,
          "V_bus": 8.166,
          "I_bus": 0.328,
          "T_eps": 13.4,
          "SOC": 79.0,
          "anomaly_type": "normal",
          "orbit_sunlight": true,
          "P_batt": 20.688568,
          "P_solar": 29.683415,
          "P_bus": 2.6784480000000004,
          "converter_ratio": 0.5147179325559408,
          "charge_efficiency": 0.6969739836201461,
          "delta_V_batt": 0.0759999999999987,
          "delta_I_batt": 0.591,
          "delta_T_batt": -0.5999999999999996,
          "delta_V_bus": 0.0330000000000012,
          "delta_I_bus": 0.004,
          "delta_SOC": 5.5,
          "rolling_std_V_batt": 0.1178490559996081,
          "rolling_mean_V_batt": 8.171800000000001,
          "rolling_std_I_batt": 1.261249032595158,
          "rolling_mean_I_batt": 1.3973,
          "rolling_std_T_batt": 16.376137789139694,
          "rolling_mean_T_batt": 20.27,
          "V_batt_V_bus_ratio": 1.017879010531472,
          "power_balance": 6.316399000000003
        },
        {
          "timestamp": "2025-12-12 12:39:20.050811",
          "V_batt": 8.114,
          "I_batt": 1.505,
          "T_batt": 15.1,
          "V_solar": 16.79,
          "I_solar": 0.943,
          "V_bus": 8.044,
          "I_bus": 0.35,
          "T_eps": 13.8,
          "SOC": 68.5,
          "anomaly_type": "normal",
          "orbit_sunlight": true,
          "P_batt": 12.21157,
          "P_solar": 15.832969999999998,
          "P_bus": 2.8154,
          "converter_ratio": 0.4790946992257296,
          "charge_efficiency": 0.7712747513574523,
          "delta_V_batt": -0.1979999999999986,
          "delta_I_batt": -0.984,
          "delta_T_batt": -0.8000000000000007,
          "delta_V_bus": -0.1219999999999998,
          "delta_I_bus": 0.0219999999999999,
          "delta_SOC": -10.5,
          "rolling_std_V_batt": 0.1158228532429243,
          "rolling_mean_V_batt": 8.1584,
          "rolling_std_I_batt": 1.231497841383952,
          "rolling_mean_I_batt": 1.4856,
          "rolling_std_T_batt": 16.392735518447736,
          "rolling_mean_T_batt": 20.22,
          "V_batt_V_bus_ratio": 1.0087021382396817,
          "power_balance": 0.8059999999999978
        },
        {
          "timestamp": "2025-12-12 12:39:37.330811",
          "V_batt": 8.275,
          "I_batt": 2.554,
          "T_batt": 14.7,
          "V_solar": 15.263,
          "I_solar": 1.886,
          "V_bus": 8.136,
          "I_bus": 0.354,
          "T_eps": 14.5,
          "SOC": 77.2,
          "anomaly_type": "normal",
          "orbit_sunlight": true,
          "P_batt": 21.13435,
          "P_solar": 28.786018,
          "P_bus": 2.880144,
          "converter_ratio": 0.5330537902116228,
          "charge_efficiency": 0.7341880353163122,
          "delta_V_batt": 0.1609999999999996,
          "delta_I_batt": 1.049,
          "delta_T_batt": -0.4000000000000003,
          "delta_V_bus": 0.0919999999999987,
          "delta_I_bus": 0.004,
          "delta_SOC": 8.700000000000003,
          "rolling_std_V_batt": 0.1199630035561838,
          "rolling_mean_V_batt": 8.174700000000001,
          "rolling_std_I_batt": 1.264387967885385,
          "rolling_mean_I_batt": 1.5306,
          "rolling_std_T_batt": 16.429340285666445,
          "rolling_mean_T_batt": 20.11,
          "V_batt_V_bus_ratio": 1.017084562438545,
          "power_balance": 4.771524000000001
        },
        {
          "timestamp": "2025-12-12 12:39:54.610811",
          "V_batt": 8.262,
          "I_batt": 2.344,
          "T_batt": 15.4,
          "V_solar": 16.886,
          "I_solar": 1.374,
          "V_bus": 8.187,
          "I_bus": 0.352,
          "T_eps": 14.3,
          "SOC": 77.9,
          "anomaly_type": "normal",
          "orbit_sunlight": true,
          "P_batt": 19.366128,
          "P_solar": 23.201364,
          "P_bus": 2.8818239999999995,
          "converter_ratio": 0.4848395120217932,
          "charge_efficiency": 0.8346978220763227,
          "delta_V_batt": -0.0129999999999999,
          "delta_I_batt": -0.2099999999999999,
          "delta_T_batt": 0.7000000000000011,
          "delta_V_bus": 0.0510000000000001,
          "delta_I_bus": -0.002,
          "delta_SOC": 0.7000000000000028,
          "rolling_std_V_batt": 0.1231097071720943,
          "rolling_mean_V_batt": 8.182,
          "rolling_std_I_batt": 1.2902303885568482,
          "rolling_mean_I_batt": 1.6126999999999998,
          "rolling_std_T_batt": 16.44148209053349,
          "rolling_mean_T_batt": 20.07,
          "V_batt_V_bus_ratio": 1.0091608647856358,
          "power_balance": 0.9534120000000024
        },
        {
          "timestamp": "2025-12-12 12:40:11.890811",
          "V_batt": 8.249,
          "I_batt": 2.132,
          "T_batt": 15.6,
          "V_solar": 17.174,
          "I_solar": 1.256,
          "V_bus": 8.119,
          "I_bus": 0.363,
          "T_eps": 13.2,
          "SOC": 76.3,
          "anomaly_type": "normal",
          "orbit_sunlight": true,
          "P_batt": 17.586868000000003,
          "P_solar": 21.570544,
          "P_bus": 2.947197,
          "converter_ratio": 0.4727495050657971,
          "charge_efficiency": 0.8153187049895452,
          "delta_V_batt": -0.0129999999999999,
          "delta_I_batt": -0.2119999999999997,
          "delta_T_batt": 0.1999999999999993,
          "delta_V_bus": -0.0679999999999996,
          "delta_I_bus": 0.011,
          "delta_SOC": -1.6000000000000083,
          "rolling_std_V_batt": 0.1152335309997295,
          "rolling_mean_V_batt": 8.2019,
          "rolling_std_I_batt": 0.4792296596274782,
          "rolling_mean_I_batt": 2.0058,
          "rolling_std_T_batt": 2.056318176850217,
          "rolling_mean_T_batt": 14.98,
          "V_batt_V_bus_ratio": 1.0160118241162706,
          "power_balance": 1.036478999999996
        },
        {
          "timestamp": "2025-12-12 12:40:29.170811",
          "V_batt": 7.991,
          "I_batt": 0.595,
          "T_batt": 14.5,
          "V_solar": 16.556,
          "I_solar": 0.528,
          "V_bus": 7.948,
          "I_bus": 0.367,
          "T_eps": 12.3,
          "SOC": 61.7,
          "anomaly_type": "normal",
          "orbit_sunlight": true,
          "P_batt": 4.754645,
          "P_solar": 8.741568000000001,
          "P_bus": 2.916916,
          "converter_ratio": 0.4800676491906258,
          "charge_efficiency": 0.5439121448234459,
          "delta_V_batt": -0.2580000000000009,
          "delta_I_batt": -1.537,
          "delta_T_batt": -1.0999999999999996,
          "delta_V_bus": -0.1709999999999993,
          "delta_I_bus": 0.004,
          "delta_SOC": -14.599999999999994,
          "rolling_std_V_batt": 0.1333017045819117,
          "rolling_mean_V_batt": 8.182300000000001,
          "rolling_std_I_batt": 0.6503168116814736,
          "rolling_mean_I_batt": 1.9028,
          "rolling_std_T_batt": 0.6073622386097554,
          "rolling_mean_T_batt": 15.5,
          "V_batt_V_bus_ratio": 1.0054101660795167,
          "power_balance": 1.0700070000000008
        },
        {
          "timestamp": "2025-12-12 12:40:46.450811",
          "V_batt": 8.045,
          "I_batt": 2.085,
          "T_batt": 13.6,
          "V_solar": 15.287,
          "I_solar": 1.419,
          "V_bus": 7.929,
          "I_bus": 0.362,
          "T_eps": 12.6,
          "SOC": 64.2,
          "anomaly_type": "normal",
          "orbit_sunlight": true,
          "P_batt": 16.773825,
          "P_solar": 21.692253,
          "P_bus": 2.870298,
          "converter_ratio": 0.5186759992150193,
          "charge_efficiency": 0.7732633857810896,
          "delta_V_batt": 0.0540000000000002,
          "delta_I_batt": 1.49,
          "delta_T_batt": -0.9000000000000004,
          "delta_V_bus": -0.0190000000000001,
          "delta_I_bus": -0.005,
          "delta_SOC": 2.5,
          "rolling_std_V_batt": 0.129103963275076,
          "rolling_mean_V_batt": 8.185500000000001,
          "rolling_std_I_batt": 0.620873613905798,
          "rolling_mean_I_batt": 1.8616,
          "rolling_std_T_batt": 0.8403702887551315,
          "rolling_mean_T_batt": 15.28,
          "V_batt_V_bus_ratio": 1.0146298398284777,
          "power_balance": 2.0481300000000022
        }
      ]
    }
  }
}